{
	"info": {
		"_postman_id": "181f21fb-d2e5-4cae-9c6e-d594101a9801",
		"name": "VEHICLE RENT",
		"schema": "https://schema.getpostman.com/json/collection/v2.1.0/collection.json"
	},
	"item": [
		{
			"name": "USER",
			"item": [
				{
					"name": "LIST USER",
					"request": {
						"method": "GET",
						"header": [],
						"url": {
							"raw": "{{developmentVehicleURL}}/users?sort=id&order=desc",
							"host": [
								"{{developmentVehicleURL}}"
							],
							"path": [
								"users"
							],
							"query": [
								{
									"key": "name",
									"value": "ani",
									"disabled": true
								},
								{
									"key": "limit",
									"value": "2",
									"disabled": true
								},
								{
									"key": "page",
									"value": "2",
									"disabled": true
								},
								{
									"key": "sort",
									"value": "id"
								},
								{
									"key": "order",
									"value": "desc"
								}
							]
						}
					},
					"response": []
				},
				{
					"name": "DETAIL USER",
					"protocolProfileBehavior": {
						"disableBodyPruning": true
					},
					"request": {
						"method": "GET",
						"header": [],
						"body": {
							"mode": "urlencoded",
							"urlencoded": []
						},
						"url": {
							"raw": "{{developmentVehicleURL}}/users/:id",
							"host": [
								"{{developmentVehicleURL}}"
							],
							"path": [
								"users",
								":id"
							],
							"variable": [
								{
									"key": "id",
									"value": "4"
								}
							]
						}
					},
					"response": []
				},
				{
					"name": "ADD USER",
					"request": {
						"method": "POST",
						"header": [],
						"body": {
							"mode": "formdata",
							"formdata": [
								{
									"key": "fullName",
									"value": "aaaa",
									"type": "text"
								},
								{
									"key": "nickName",
									"value": "bbbb",
									"type": "text"
								},
								{
									"key": "gender",
									"value": "Male",
									"type": "text"
								},
								{
									"key": "address",
									"value": "aaaa",
									"type": "text"
								},
								{
									"key": "birthDate",
									"value": "2022-01-22",
									"type": "text"
								},
								{
									"key": "mobileNumber",
									"value": "08124445544",
									"type": "text"
								},
								{
									"key": "email",
									"value": "aaa@mail.com",
									"type": "text"
								},
								{
									"key": "username",
									"value": "aaa01",
									"type": "text"
								},
								{
									"key": "password",
									"value": "123",
									"type": "text"
								},
								{
									"key": "role",
									"value": "customer",
									"type": "text"
								},
								{
									"key": "photo",
									"type": "file",
									"src": "/C:/Users/SELLA/Pictures/oceanicon.jpg"
								}
							]
						},
						"url": {
							"raw": "{{developmentVehicleURL}}/users",
							"host": [
								"{{developmentVehicleURL}}"
							],
							"path": [
								"users"
							]
						}
					},
					"response": []
				},
				{
					"name": "UPDATE USER",
					"request": {
						"method": "PUT",
						"header": [],
						"body": {
							"mode": "formdata",
							"formdata": [
								{
									"key": "fullName",
									"value": "Delyn Mayer",
									"type": "text"
								},
								{
									"key": "nickName",
									"value": "Delin",
									"type": "text"
								},
								{
									"key": "gender",
									"value": "Male",
									"type": "text"
								},
								{
									"key": "address",
									"value": "Jl. ABC no 10",
									"type": "text"
								},
								{
									"key": "birthDate",
									"value": "2022-01-24",
									"type": "text"
								},
								{
									"key": "mobileNumber",
									"value": "0821234343",
									"type": "text"
								},
								{
									"key": "email",
									"value": "delin@mail.com",
									"type": "text"
								},
								{
									"key": "username",
									"value": "delin01",
									"type": "text"
								},
								{
									"key": "password",
									"value": "123",
									"type": "text"
								},
								{
									"key": "role",
									"value": "customer",
									"type": "text"
								},
								{
									"key": "photo",
									"type": "file",
									"src": "/C:/Users/SELLA/Pictures/dark34.jpg"
								}
							]
						},
						"url": {
							"raw": "{{developmentVehicleURL}}/users/:id",
							"host": [
								"{{developmentVehicleURL}}"
							],
							"path": [
								"users",
								":id"
							],
							"variable": [
								{
									"key": "id",
									"value": "14"
								}
							]
						}
					},
					"response": []
				},
				{
					"name": "UPDATE USER",
					"request": {
						"method": "PATCH",
						"header": [],
						"body": {
							"mode": "formdata",
							"formdata": [
								{
									"key": "fullName",
									"value": "",
									"type": "text",
									"disabled": true
								},
								{
									"key": "nickName",
									"value": "",
									"type": "text",
									"disabled": true
								},
								{
									"key": "gender",
									"value": "Female",
									"type": "text"
								},
								{
									"key": "address",
									"value": "",
									"type": "text",
									"disabled": true
								},
								{
									"key": "birthDate",
									"value": "2022-01-09",
									"type": "text"
								},
								{
									"key": "mobileNumber",
									"value": "081234567",
									"type": "text"
								},
								{
									"key": "email",
									"value": "dogsegies@gmail.com",
									"type": "text"
								},
								{
									"key": "username",
									"value": "ani01",
									"type": "text"
								},
								{
									"key": "isVerified",
									"value": "1",
									"type": "text",
									"disabled": true
								},
								{
									"key": "password",
									"value": "",
									"type": "text",
									"disabled": true
								},
								{
									"key": "photo",
									"type": "file",
									"src": "/C:/Users/SELLA/Pictures/Danbo.jpg"
								}
							]
						},
						"url": {
							"raw": "{{developmentVehicleURL}}/users/:id",
							"host": [
								"{{developmentVehicleURL}}"
							],
							"path": [
								"users",
								":id"
							],
							"variable": [
								{
									"key": "id",
									"value": "4"
								}
							]
						}
					},
					"response": []
				},
				{
					"name": "DELETE USER",
					"request": {
						"method": "DELETE",
						"header": [],
						"body": {
							"mode": "urlencoded",
							"urlencoded": []
						},
						"url": {
							"raw": "{{developmentVehicleURL}}/users/:id",
							"host": [
								"{{developmentVehicleURL}}"
							],
							"path": [
								"users",
								":id"
							],
							"variable": [
								{
									"key": "id",
									"value": "24"
								}
							]
						}
					},
					"response": []
				}
			]
		},
		{
			"name": "VEHICLE",
			"item": [
				{
					"name": "LIST VEHICLE",
					"request": {
						"method": "GET",
						"header": [],
						"url": {
							"raw": "{{developmentVehicleURL}}/vehicles?name=honda",
							"host": [
								"{{developmentVehicleURL}}"
							],
							"path": [
								"vehicles"
							],
							"query": [
								{
									"key": "name",
									"value": "honda"
								},
								{
									"key": "page",
									"value": "3",
									"disabled": true
								},
								{
									"key": "limit",
									"value": "5",
									"disabled": true
								},
								{
									"key": "sort",
									"value": "id",
									"disabled": true
								},
								{
									"key": "order",
									"value": "desc",
									"disabled": true
								}
							]
						}
					},
					"response": []
				},
				{
					"name": "DETAIL VEHICLE",
					"protocolProfileBehavior": {
						"disableBodyPruning": true
					},
					"request": {
						"method": "GET",
						"header": [],
						"body": {
							"mode": "urlencoded",
							"urlencoded": []
						},
						"url": {
							"raw": "{{developmentVehicleURL}}/vehicles/:id",
							"host": [
								"{{developmentVehicleURL}}"
							],
							"path": [
								"vehicles",
								":id"
							],
							"variable": [
								{
									"key": "id",
									"value": "34"
								}
							]
						}
					},
					"response": []
				},
				{
					"name": "CATEGORY VEHICLE",
					"request": {
						"method": "GET",
						"header": [],
						"url": {
							"raw": "{{developmentVehicleURL}}/vehicles/category/:id?sort=id&order=desc",
							"host": [
								"{{developmentVehicleURL}}"
							],
							"path": [
								"vehicles",
								"category",
								":id"
							],
							"query": [
								{
									"key": "page",
									"value": "",
									"disabled": true
								},
								{
									"key": "sort",
									"value": "id"
								},
								{
									"key": "order",
									"value": "desc"
								}
							],
							"variable": [
								{
									"key": "id",
									"value": "2"
								}
							]
						}
					},
					"response": []
				},
				{
					"name": "ADD VEHICLE",
					"request": {
						"method": "POST",
						"header": [
							{
								"key": "Accept",
								"value": "application/json",
								"type": "text"
							}
						],
						"body": {
							"mode": "formdata",
							"formdata": [
								{
									"key": "name",
									"value": "aaaa",
									"type": "text"
								},
								{
									"key": "category_id",
									"value": "2",
									"type": "text"
								},
								{
									"key": "location_id",
									"value": "4",
									"type": "text"
								},
								{
									"key": "price",
									"value": "100000",
									"type": "text"
								},
								{
									"key": "qty",
									"value": "8",
									"type": "text"
								},
								{
									"key": "isAvailable",
									"value": "1",
									"type": "text"
								},
								{
									"key": "description",
									"value": "ddefefefef",
									"type": "text"
								},
								{
									"key": "photo",
									"type": "file",
									"src": "/C:/Users/SELLA/Pictures/portofolio/loginadmin.JPG"
								}
							]
						},
						"url": {
							"raw": "{{developmentVehicleURL}}/vehicles",
							"host": [
								"{{developmentVehicleURL}}"
							],
							"path": [
								"vehicles"
							]
						}
					},
					"response": []
				},
				{
					"name": "UPDATE VEHICLE",
					"request": {
						"method": "PATCH",
						"header": [],
						"body": {
							"mode": "formdata",
							"formdata": [
								{
									"key": "name",
									"value": "Fixie Gray",
									"type": "text"
								},
								{
									"key": "category_id",
									"value": "1",
									"type": "text"
								},
								{
									"key": "location_id",
									"value": "1",
									"type": "text"
								},
								{
									"key": "price",
									"value": "",
									"type": "text"
								},
								{
									"key": "qty",
									"value": "",
									"type": "text"
								},
								{
									"key": "isAvailable",
									"value": "",
									"type": "text"
								},
								{
									"key": "photo",
									"type": "file",
									"src": "/C:/Users/SELLA/Documents/Fazztrack/fw5-backend-begineer(tugas)/uploads/fixie-gray.png",
									"disabled": true
								}
							]
						},
						"url": {
							"raw": "{{developmentVehicleURL}}/vehicles/:id",
							"host": [
								"{{developmentVehicleURL}}"
							],
							"path": [
								"vehicles",
								":id"
							],
							"variable": [
								{
									"key": "id",
									"value": "34"
								}
							]
						}
					},
					"response": []
				},
				{
					"name": "DELETE VEHICLE",
					"request": {
						"method": "DELETE",
						"header": [],
						"url": {
							"raw": "{{developmentVehicleURL}}/vehicles/:id",
							"host": [
								"{{developmentVehicleURL}}"
							],
							"path": [
								"vehicles",
								":id"
							],
							"variable": [
								{
									"key": "id",
									"value": "44"
								}
							]
						}
					},
					"response": []
				},
				{
					"name": "LIST POPULAR VEHICLE",
					"request": {
						"method": "GET",
						"header": [],
						"url": {
							"raw": "{{developmentVehicleURL}}/vehicles/popular?sort=total&order=desc",
							"host": [
								"{{developmentVehicleURL}}"
							],
							"path": [
								"vehicles",
								"popular"
							],
							"query": [
								{
									"key": "sort",
									"value": "total"
								},
								{
									"key": "order",
									"value": "desc"
								}
							]
						}
					},
					"response": []
				}
			]
		},
		{
			"name": "VEHICLE IMAGE",
			"item": [
				{
					"name": "LIST VEHICLE IMAGE",
					"request": {
						"method": "GET",
						"header": [],
						"url": {
							"raw": "{{baseURL}}/vehicle-images?name=honda",
							"host": [
								"{{baseURL}}"
							],
							"path": [
								"vehicle-images"
							],
							"query": [
								{
									"key": "name",
									"value": "honda"
								},
								{
									"key": "page",
									"value": "3",
									"disabled": true
								},
								{
									"key": "limit",
									"value": "5",
									"disabled": true
								},
								{
									"key": "sort",
									"value": "id",
									"disabled": true
								},
								{
									"key": "order",
									"value": "desc",
									"disabled": true
								}
							]
						}
					},
					"response": []
				},
				{
					"name": "DETAIL VEHICLE IMAGE",
					"protocolProfileBehavior": {
						"disableBodyPruning": true
					},
					"request": {
						"method": "GET",
						"header": [],
						"body": {
							"mode": "urlencoded",
							"urlencoded": []
						},
						"url": {
							"raw": "{{baseURL}}/vehicle-images/:id",
							"host": [
								"{{baseURL}}"
							],
							"path": [
								"vehicle-images",
								":id"
							],
							"variable": [
								{
									"key": "id",
									"value": "34"
								}
							]
						}
					},
					"response": []
				},
				{
					"name": "LIST VEHICLE IMAGE BY VEHICLE",
					"request": {
						"method": "GET",
						"header": [],
						"url": {
							"raw": "{{baseURL}}/vehicle-images/vehicle/:id?sort=id&order=desc",
							"host": [
								"{{baseURL}}"
							],
							"path": [
								"vehicle-images",
								"vehicle",
								":id"
							],
							"query": [
								{
									"key": "page",
									"value": "",
									"disabled": true
								},
								{
									"key": "sort",
									"value": "id"
								},
								{
									"key": "order",
									"value": "desc"
								}
							],
							"variable": [
								{
									"key": "id",
									"value": "5"
								}
							]
						}
					},
					"response": []
				},
				{
					"name": "ADD VEHICLE IMAGE",
					"request": {
						"method": "POST",
						"header": [
							{
								"key": "Accept",
								"value": "application/json",
								"type": "text"
							}
						],
						"body": {
							"mode": "formdata",
							"formdata": [
								{
									"key": "vehicle_id",
									"value": "5",
									"type": "text"
								},
								{
									"key": "photo",
									"type": "file",
									"src": "/C:/Users/SELLA/Pictures/logo2.png"
								}
							]
						},
						"url": {
							"raw": "{{baseURL}}/vehicle-images",
							"host": [
								"{{baseURL}}"
							],
							"path": [
								"vehicle-images"
							]
						}
					},
					"response": []
				},
				{
					"name": "UPDATE VEHICLE IMAGE",
					"request": {
						"method": "PATCH",
						"header": [],
						"body": {
							"mode": "formdata",
							"formdata": [
								{
									"key": "vehicle_id",
									"value": "6",
									"type": "text"
								},
								{
									"key": "isPrimary",
									"value": "1",
									"type": "text"
								},
								{
									"key": "photo",
									"type": "file",
									"src": "/C:/Users/SELLA/Documents/CV dan Porfofolio Marsella.docx"
								}
							]
						},
						"url": {
							"raw": "{{baseURL}}/vehicle-images/:id",
							"host": [
								"{{baseURL}}"
							],
							"path": [
								"vehicle-images",
								":id"
							],
							"variable": [
								{
									"key": "id",
									"value": "1"
								}
							]
						}
					},
					"response": []
				},
				{
					"name": "DELETE VEHICLE IMAGE",
					"request": {
						"method": "DELETE",
						"header": [],
						"url": {
							"raw": "{{baseURL}}/vehicle-images/:id",
							"host": [
								"{{baseURL}}"
							],
							"path": [
								"vehicle-images",
								":id"
							],
							"variable": [
								{
									"key": "id",
									"value": "3"
								}
							]
						}
					},
					"response": []
				}
			]
		},
		{
			"name": "HISTORY",
			"item": [
				{
					"name": "LIST HISTORY",
					"request": {
						"method": "GET",
						"header": [],
						"url": {
							"raw": "{{developmentVehicleURL}}/histories?search=TOYOTA&sort=id&order=desc",
							"host": [
								"{{developmentVehicleURL}}"
							],
							"path": [
								"histories"
							],
							"query": [
								{
									"key": "search",
									"value": "TOYOTA"
								},
								{
									"key": "limit",
									"value": "2",
									"disabled": true
								},
								{
									"key": "page",
									"value": "2",
									"disabled": true
								},
								{
									"key": "location",
									"value": "",
									"disabled": true
								},
								{
									"key": "category_id",
									"value": "",
									"disabled": true
								},
								{
									"key": "status_id",
									"value": "",
									"disabled": true
								},
								{
									"key": "date",
									"value": "",
									"disabled": true
								},
								{
									"key": "sort",
									"value": "id"
								},
								{
									"key": "order",
									"value": "desc"
								}
							]
						}
					},
					"response": []
				},
				{
					"name": "LIST HISTORY BY USER ID",
					"request": {
						"method": "GET",
						"header": [],
						"url": {
							"raw": "{{developmentVehicleURL}}/histories?search=TOYOTA&sort=id&order=desc",
							"host": [
								"{{developmentVehicleURL}}"
							],
							"path": [
								"histories"
							],
							"query": [
								{
									"key": "search",
									"value": "TOYOTA"
								},
								{
									"key": "limit",
									"value": "2",
									"disabled": true
								},
								{
									"key": "page",
									"value": "2",
									"disabled": true
								},
								{
									"key": "location",
									"value": "",
									"disabled": true
								},
								{
									"key": "category_id",
									"value": "",
									"disabled": true
								},
								{
									"key": "status_id",
									"value": "",
									"disabled": true
								},
								{
									"key": "date",
									"value": "",
									"disabled": true
								},
								{
									"key": "sort",
									"value": "id"
								},
								{
									"key": "order",
									"value": "desc"
								}
							]
						}
					},
					"response": []
				},
				{
					"name": "DETAIL HISTORY",
					"request": {
						"method": "GET",
						"header": [],
						"url": {
							"raw": "{{developmentVehicleURL}}/histories/:id",
							"host": [
								"{{developmentVehicleURL}}"
							],
							"path": [
								"histories",
								":id"
							],
							"variable": [
								{
									"key": "id",
									"value": "3"
								}
							]
						}
					},
					"response": []
				},
				{
					"name": "ADD HISTORY",
					"request": {
						"method": "POST",
						"header": [],
						"body": {
							"mode": "urlencoded",
							"urlencoded": [
								{
									"key": "idUser",
									"value": "2",
									"type": "text"
								},
								{
									"key": "idVehicle",
									"value": "10",
									"type": "text"
								},
								{
									"key": "startRentDate",
									"value": "2022-01-23",
									"type": "text"
								},
								{
									"key": "endRentDate",
									"value": "2022-01-29",
									"type": "text"
								},
								{
									"key": "prepayment",
									"value": "0",
									"type": "text"
								},
								{
									"key": "status",
									"value": "1",
									"type": "text"
								},
								{
									"key": "fullname",
									"value": "aaaa",
									"type": "text"
								},
								{
									"key": "mobilePhone",
									"value": "1234567890",
									"type": "text"
								},
								{
									"key": "location",
									"value": "Bandung",
									"type": "text"
								},
								{
									"key": "payment_id",
									"value": "2",
									"type": "text"
								},
								{
									"key": "emailAddress",
									"value": "aaaa@mail.com",
									"type": "text"
								},
								{
									"key": "idCard",
									"value": "2122121",
									"type": "text"
								},
								{
									"key": "qty",
									"value": "10",
									"type": "text"
								}
							]
						},
						"url": {
							"raw": "{{developmentVehicleURL}}/histories",
							"host": [
								"{{developmentVehicleURL}}"
							],
							"path": [
								"histories"
							]
						}
					},
					"response": []
				},
				{
					"name": "UPDATE HISTORY",
					"request": {
						"method": "PUT",
						"header": [],
						"body": {
							"mode": "urlencoded",
							"urlencoded": [
								{
									"key": "idUser",
									"value": "2",
									"type": "text"
								},
								{
									"key": "idVehicle",
									"value": "3",
									"type": "text"
								},
								{
									"key": "startRentDate",
									"value": "2022-01-07",
									"type": "text"
								},
								{
									"key": "endRentDate",
									"value": "2022-01-09",
									"type": "text"
								},
								{
									"key": "prepayment",
									"value": "100000",
									"type": "text"
								},
								{
									"key": "status",
									"value": "1",
									"type": "text"
								},
								{
									"key": "fullname",
									"value": "aaaaa",
									"type": "text"
								},
								{
									"key": "mobilePhone",
									"value": "08132233232",
									"type": "text"
								},
								{
									"key": "location",
									"value": "Bandung",
									"type": "text"
								},
								{
									"key": "payment_id",
									"value": "1",
									"type": "text"
								},
								{
									"key": "emailAddress",
									"value": "aaaa@mail.com",
									"type": "text"
								},
								{
									"key": "idCard",
									"value": "12345",
									"type": "text"
								},
								{
									"key": "qty",
									"value": "4",
									"type": "text"
								}
							]
						},
						"url": {
							"raw": "{{developmentVehicleURL}}/histories/:id",
							"host": [
								"{{developmentVehicleURL}}"
							],
							"path": [
								"histories",
								":id"
							],
							"variable": [
								{
									"key": "id",
									"value": "14"
								}
							]
						}
					},
					"response": []
				},
				{
					"name": "UPDATE HISTORY",
					"request": {
						"method": "PATCH",
						"header": [],
						"body": {
							"mode": "urlencoded",
							"urlencoded": [
								{
									"key": "user_id",
									"value": "2",
									"type": "text"
								},
								{
									"key": "vehicle_id",
									"value": "7",
									"type": "text"
								},
								{
									"key": "rentStartDate",
									"value": "2022-04-07",
									"type": "text"
								},
								{
									"key": "rentEndDate",
									"value": "2022-04-09",
									"type": "text"
								},
								{
									"key": "prepayment",
									"value": "0",
									"type": "text"
								},
								{
									"key": "status_id",
									"value": "2",
									"type": "text"
								},
								{
									"key": "fullname",
									"value": "Andi",
									"type": "text"
								},
								{
									"key": "mobilePhone",
									"value": "1234567890",
									"type": "text"
								},
								{
									"key": "location",
									"value": "Bandung",
									"type": "text",
									"disabled": true
								},
								{
									"key": "payment_id",
									"value": "2",
									"type": "text"
								},
								{
									"key": "emailAddress",
									"value": "andi@mail.com",
									"type": "text"
								},
								{
									"key": "idCard",
									"value": "12345",
									"type": "text",
									"disabled": true
								},
								{
									"key": "qty",
									"value": "5",
									"type": "text"
								}
							]
						},
						"url": {
							"raw": "{{developmentVehicleURL}}/histories/:id",
							"host": [
								"{{developmentVehicleURL}}"
							],
							"path": [
								"histories",
								":id"
							],
							"variable": [
								{
									"key": "id",
									"value": "14"
								}
							]
						}
					},
					"response": []
				},
				{
					"name": "DELETE HISTORY",
					"request": {
						"method": "DELETE",
						"header": [],
						"url": {
							"raw": "{{developmentVehicleURL}}/histories/:id",
							"host": [
								"{{developmentVehicleURL}}"
							],
							"path": [
								"histories",
								":id"
							],
							"variable": [
								{
									"key": "id",
									"value": "14"
								}
							]
						}
					},
					"response": []
				},
				{
					"name": "New Request",
					"request": {
						"method": "GET",
						"header": []
					},
					"response": []
				}
			]
		},
		{
			"name": "CATEGORY",
			"item": [
				{
					"name": "LIST CATEGORY",
					"request": {
						"method": "GET",
						"header": [],
						"url": {
							"raw": "{{developmentVehicleURL}}/categories",
							"host": [
								"{{developmentVehicleURL}}"
							],
							"path": [
								"categories"
							],
							"query": [
								{
									"key": "search",
									"value": "car",
									"disabled": true
								},
								{
									"key": "page",
									"value": "",
									"disabled": true
								},
								{
									"key": "limit",
									"value": "",
									"disabled": true
								},
								{
									"key": "sort",
									"value": "name",
									"disabled": true
								},
								{
									"key": "order",
									"value": "asc",
									"disabled": true
								}
							]
						}
					},
					"response": []
				},
				{
					"name": "DETAIL CATEGORY",
					"request": {
						"method": "GET",
						"header": [],
						"url": {
							"raw": "{{developmentVehicleURL}}/categories/:id",
							"host": [
								"{{developmentVehicleURL}}"
							],
							"path": [
								"categories",
								":id"
							],
							"variable": [
								{
									"key": "id",
									"value": "2"
								}
							]
						}
					},
					"response": []
				},
				{
					"name": "ADD CATEGORY",
					"request": {
						"method": "POST",
						"header": [],
						"body": {
							"mode": "urlencoded",
							"urlencoded": [
								{
									"key": "name",
									"value": "bike",
									"type": "text"
								}
							]
						},
						"url": {
							"raw": "{{developmentVehicleURL}}/categories",
							"host": [
								"{{developmentVehicleURL}}"
							],
							"path": [
								"categories"
							]
						}
					},
					"response": []
				},
				{
					"name": "UPDATE CATEGORY",
					"request": {
						"method": "PUT",
						"header": [],
						"body": {
							"mode": "urlencoded",
							"urlencoded": [
								{
									"key": "name",
									"value": "cccc",
									"type": "text"
								}
							]
						},
						"url": {
							"raw": "{{developmentVehicleURL}}/categories/:id",
							"host": [
								"{{developmentVehicleURL}}"
							],
							"path": [
								"categories",
								":id"
							],
							"variable": [
								{
									"key": "id",
									"value": "4"
								}
							]
						}
					},
					"response": []
				},
				{
					"name": "DELETE CATEGORY",
					"request": {
						"method": "DELETE",
						"header": [],
						"url": {
							"raw": "{{developmentVehicleURL}}/categories/:id",
							"host": [
								"{{developmentVehicleURL}}"
							],
							"path": [
								"categories",
								":id"
							],
							"variable": [
								{
									"key": "id",
									"value": "4"
								}
							]
						}
					},
					"response": []
				}
			]
		},
		{
			"name": "LOCATION",
			"item": [
				{
					"name": "LIST LOCATION",
					"request": {
						"method": "GET",
						"header": [],
						"url": {
							"raw": "{{developmentVehicleURL}}/locations",
							"host": [
								"{{developmentVehicleURL}}"
							],
							"path": [
								"locations"
							],
							"query": [
								{
									"key": "search",
									"value": "jak",
									"disabled": true
								},
								{
									"key": "page",
									"value": "",
									"disabled": true
								},
								{
									"key": "limit",
									"value": "",
									"disabled": true
								},
								{
									"key": "sort",
									"value": "name",
									"disabled": true
								},
								{
									"key": "order",
									"value": "asc",
									"disabled": true
								}
							]
						}
					},
					"response": []
				},
				{
					"name": "DETAIL LOCATION",
					"request": {
						"method": "GET",
						"header": [],
						"url": {
							"raw": "{{developmentVehicleURL}}/locations/:id",
							"host": [
								"{{developmentVehicleURL}}"
							],
							"path": [
								"locations",
								":id"
							],
							"variable": [
								{
									"key": "id",
									"value": "2"
								}
							]
						}
					},
					"response": []
				},
				{
					"name": "ADD LOCATION",
					"request": {
						"method": "POST",
						"header": [],
						"body": {
							"mode": "urlencoded",
							"urlencoded": [
								{
									"key": "location",
									"value": "",
									"type": "text"
								}
							]
						},
						"url": {
							"raw": "{{developmentVehicleURL}}/locations",
							"host": [
								"{{developmentVehicleURL}}"
							],
							"path": [
								"locations"
							]
						}
					},
					"response": []
				},
				{
					"name": "UPDATE LOCATION",
					"request": {
						"method": "PUT",
						"header": [],
						"body": {
							"mode": "urlencoded",
							"urlencoded": [
								{
									"key": "location",
									"value": "Kalimantan",
									"type": "text"
								}
							]
						},
						"url": {
							"raw": "{{developmentVehicleURL}}/locations/:id",
							"host": [
								"{{developmentVehicleURL}}"
							],
							"path": [
								"locations",
								":id"
							],
							"variable": [
								{
									"key": "id",
									"value": "4"
								}
							]
						}
					},
					"response": []
				},
				{
					"name": "DELETE LOCATION",
					"request": {
						"method": "DELETE",
						"header": [],
						"url": {
							"raw": "{{developmentVehicleURL}}/locations/:id",
							"host": [
								"{{developmentVehicleURL}}"
							],
							"path": [
								"locations",
								":id"
							],
							"variable": [
								{
									"key": "id",
									"value": "14"
								}
							]
						}
					},
					"response": []
				}
			]
		},
		{
			"name": "PAYMENT_TYPE",
			"item": [
				{
					"name": "LIST PAYMENT TYPE",
					"request": {
						"method": "GET",
						"header": [],
						"url": {
							"raw": "{{developmentVehicleURL}}/payment-types?search=cas",
							"host": [
								"{{developmentVehicleURL}}"
							],
							"path": [
								"payment-types"
							],
							"query": [
								{
									"key": "search",
									"value": "cas"
								},
								{
									"key": "page",
									"value": "2",
									"disabled": true
								},
								{
									"key": "limit",
									"value": "2",
									"disabled": true
								},
								{
									"key": "sort",
									"value": "name",
									"disabled": true
								},
								{
									"key": "order",
									"value": "asc",
									"disabled": true
								}
							]
						}
					},
					"response": []
				},
				{
					"name": "DETAIL PAYMENT TYPE",
					"request": {
						"method": "GET",
						"header": [],
						"url": {
							"raw": "{{developmentVehicleURL}}/payment-types/:id",
							"host": [
								"{{developmentVehicleURL}}"
							],
							"path": [
								"payment-types",
								":id"
							],
							"variable": [
								{
									"key": "id",
									"value": "4"
								}
							]
						}
					},
					"response": []
				},
				{
					"name": "ADD PAYMENT TYPE",
					"request": {
						"method": "POST",
						"header": [],
						"body": {
							"mode": "urlencoded",
							"urlencoded": [
								{
									"key": "payment",
									"value": "ferfrfr",
									"type": "text"
								}
							]
						},
						"url": {
							"raw": "{{developmentVehicleURL}}/payment-types",
							"host": [
								"{{developmentVehicleURL}}"
							],
							"path": [
								"payment-types"
							]
						}
					},
					"response": []
				},
				{
					"name": "UPDATE PAYMENT TYPE",
					"request": {
						"method": "PUT",
						"header": [],
						"body": {
							"mode": "urlencoded",
							"urlencoded": [
								{
									"key": "payment",
									"value": "cccc",
									"type": "text"
								}
							]
						},
						"url": {
							"raw": "{{developmentVehicleURL}}/payment-types/:id",
							"host": [
								"{{developmentVehicleURL}}"
							],
							"path": [
								"payment-types",
								":id"
							],
							"variable": [
								{
									"key": "id",
									"value": "14"
								}
							]
						}
					},
					"response": []
				},
				{
					"name": "DELETE PAYMENT TYPE",
					"request": {
						"method": "DELETE",
						"header": [],
						"url": {
							"raw": "{{developmentVehicleURL}}/payment-types/:id",
							"host": [
								"{{developmentVehicleURL}}"
							],
							"path": [
								"payment-types",
								":id"
							],
							"variable": [
								{
									"key": "id",
									"value": "14"
								}
							]
						}
					},
					"response": []
				}
			]
		},
		{
			"name": "STATUS",
			"item": [
				{
					"name": "LIST STATUS",
					"request": {
						"method": "GET",
						"header": [],
						"url": {
							"raw": "{{developmentVehicleURL}}/status",
							"host": [
								"{{developmentVehicleURL}}"
							],
							"path": [
								"status"
							],
							"query": [
								{
									"key": "search",
									"value": "waiting",
									"disabled": true
								}
							]
						}
					},
					"response": []
				},
				{
					"name": "DETAIL STATUS",
					"request": {
						"method": "GET",
						"header": [],
						"url": {
							"raw": "{{developmentVehicleURL}}/status/:id",
							"host": [
								"{{developmentVehicleURL}}"
							],
							"path": [
								"status",
								":id"
							],
							"variable": [
								{
									"key": "id",
									"value": "4"
								}
							]
						}
					},
					"response": []
				},
				{
					"name": "ADD STATUS",
					"request": {
						"method": "POST",
						"header": [],
						"body": {
							"mode": "urlencoded",
							"urlencoded": [
								{
									"key": "status",
									"value": "aaaa",
									"type": "text"
								}
							]
						},
						"url": {
							"raw": "{{developmentVehicleURL}}/status",
							"host": [
								"{{developmentVehicleURL}}"
							],
							"path": [
								"status"
							]
						}
					},
					"response": []
				},
				{
					"name": "UPDATE STATUS",
					"request": {
						"method": "PUT",
						"header": [],
						"body": {
							"mode": "urlencoded",
							"urlencoded": [
								{
									"key": "status",
									"value": "bbb",
									"type": "text"
								}
							]
						},
						"url": {
							"raw": "{{developmentVehicleURL}}/status/:id",
							"host": [
								"{{developmentVehicleURL}}"
							],
							"path": [
								"status",
								":id"
							],
							"variable": [
								{
									"key": "id",
									"value": "14"
								}
							]
						}
					},
					"response": []
				},
				{
					"name": "DELETE STATUS",
					"request": {
						"method": "DELETE",
						"header": [],
						"url": {
							"raw": "{{developmentVehicleURL}}/status/:id",
							"host": [
								"{{developmentVehicleURL}}"
							],
							"path": [
								"status",
								":id"
							],
							"variable": [
								{
									"key": "id",
									"value": "14"
								}
							]
						}
					},
					"response": []
				}
			]
		},
		{
			"name": "AUTH",
			"item": [
				{
					"name": "LOGIN",
					"request": {
						"method": "POST",
						"header": [],
						"body": {
							"mode": "urlencoded",
							"urlencoded": [
								{
									"key": "email",
									"value": "admin@mail.com",
									"type": "text"
								},
								{
									"key": "password",
									"value": "123",
									"type": "text"
								}
							]
						},
						"url": {
							"raw": "{{developmentVehicleURL}}/auth/login",
							"host": [
								"{{developmentVehicleURL}}"
							],
							"path": [
								"auth",
								"login"
							]
						}
					},
					"response": []
				},
				{
					"name": "REGISTER",
					"request": {
						"method": "POST",
						"header": [],
						"body": {
							"mode": "urlencoded",
							"urlencoded": [
								{
									"key": "fullName",
									"value": "ani",
									"type": "text"
								},
								{
									"key": "username",
									"value": "ani01",
									"type": "text"
								},
								{
									"key": "email",
									"value": "dogsegies@gmail.com",
									"type": "text"
								},
								{
									"key": "password",
									"value": "123",
									"type": "text"
								},
								{
									"key": "mobileNumber",
									"value": "08123456",
									"type": "text"
								}
							]
						},
						"url": {
							"raw": "{{developmentVehicleURL}}/auth/register",
							"host": [
								"{{developmentVehicleURL}}"
							],
							"path": [
								"auth",
								"register"
							]
						}
					},
					"response": []
				},
				{
					"name": "EMAIL VERIFY",
					"request": {
						"method": "POST",
						"header": [],
						"body": {
							"mode": "urlencoded",
							"urlencoded": [
								{
									"key": "email",
									"value": "dogsegies@gmail.com",
									"type": "text"
								},
								{
									"key": "password",
									"value": "123",
									"type": "text"
								},
								{
									"key": "code",
									"value": "508049",
									"type": "text"
								}
							]
						},
						"url": {
							"raw": "{{developmentVehicleURL}}/auth/emailverification",
							"host": [
								"{{developmentVehicleURL}}"
							],
							"path": [
								"auth",
								"emailverification"
							]
						}
					},
					"response": []
				},
				{
					"name": "FORGOT PASSWORD",
					"request": {
						"method": "POST",
						"header": [],
						"body": {
							"mode": "urlencoded",
							"urlencoded": [
								{
									"key": "email",
									"value": "dogsegies@gmail.com",
									"type": "text"
								},
								{
									"key": "code",
									"value": "816341",
									"type": "text"
								},
								{
									"key": "password",
									"value": "1234",
									"type": "text"
								},
								{
									"key": "confirmPassword",
									"value": "1234",
									"type": "text"
								}
							]
						},
						"url": {
							"raw": "{{developmentVehicleURL}}/auth/forgotpassword",
							"host": [
								"{{developmentVehicleURL}}"
							],
							"path": [
								"auth",
								"forgotpassword"
							]
						}
					},
					"response": []
				},
				{
					"name": "CHANGE PASSWORD",
					"request": {
						"method": "POST",
						"header": [],
						"body": {
							"mode": "urlencoded",
							"urlencoded": [
								{
									"key": "password",
									"value": "123",
									"type": "text"
								},
								{
									"key": "newPassword",
									"value": "1234",
									"type": "text"
								},
								{
									"key": "confirmNewPassword",
									"value": "1234",
									"type": "text"
								}
							]
						},
						"url": {
							"raw": "{{baseURL}}/auth/changepassword",
							"host": [
								"{{baseURL}}"
							],
							"path": [
								"auth",
								"changepassword"
							],
							"query": [
								{
									"key": "",
									"value": null,
									"disabled": true
								}
							]
						}
					},
					"response": []
				}
			]
		},
		{
			"name": "PROFILE",
			"request": {
				"method": "GET",
				"header": [],
				"url": {
					"raw": "{{developmentVehicleURL}}/profile",
					"host": [
						"{{developmentVehicleURL}}"
					],
					"path": [
						"profile"
					]
				}
			},
			"response": []
		},
		{
			"name": "SEARCH",
			"request": {
				"method": "GET",
				"header": [],
				"url": {
					"raw": "{{developmentVehicleURL}}/search?isAvailable=1&location_id=1&price_start=100000&price_end=150000",
					"host": [
						"{{developmentVehicleURL}}"
					],
					"path": [
						"search"
					],
					"query": [
						{
							"key": "payment_id",
							"value": "1",
							"disabled": true
						},
						{
							"key": "date",
							"value": "",
							"disabled": true
						},
						{
							"key": "category_id",
							"value": "3",
							"disabled": true
						},
						{
							"key": "sort",
							"value": "price",
							"disabled": true
						},
						{
							"key": "order",
							"value": "desc",
							"disabled": true
						},
						{
							"key": "name",
							"value": "honda",
							"disabled": true
						},
						{
							"key": "location",
							"value": "2",
							"disabled": true
						},
						{
							"key": "isAvailable",
							"value": "1"
						},
						{
							"key": "location_id",
							"value": "1"
						},
						{
							"key": "limit",
							"value": "5",
							"disabled": true
						},
						{
							"key": "price_start",
							"value": "100000"
						},
						{
							"key": "price_end",
							"value": "150000"
						},
						{
							"key": "status_id",
							"value": "6",
							"disabled": true
						},
						{
							"key": "rate_start",
							"value": null,
							"disabled": true
						},
						{
							"key": "rate_end",
							"value": null,
							"disabled": true
						}
					]
				}
			},
			"response": []
		}
	],
	"auth": {
		"type": "bearer",
		"bearer": [
			{
				"key": "token",
				"value": "{{token}}",
				"type": "string"
			}
		]
	},
	"event": [
		{
			"listen": "prerequest",
			"script": {
				"type": "text/javascript",
				"exec": [
					""
				]
			}
		},
		{
			"listen": "test",
			"script": {
				"type": "text/javascript",
				"exec": [
					""
				]
			}
		}
	]
}